win11_notificationbar/__init__.py
win11_notificationbar/c_structures.py
win11_notificationbar/win11_notificationbar.py
win11_notificationbar-0.0.2.dist-info/LICENSE
win11_notificationbar-0.0.2.dist-info/METADATA
win11_notificationbar-0.0.2.dist-info/WHEEL
win11_notificationbar-0.0.2.dist-info/top_level.txt
win11_notificationbar-0.0.2.dist-info/RECORD
