Metadata-Version: 2.1
Name: win11_notificationbar
Version: 0.0.2
Summary: win11_notificationbar
Home-page: 
Author: UF4
Author-email: uf4hp@foxmail.com
Classifier: Programming Language :: Python :: 3
Classifier: License :: OSI Approved :: MIT License
Classifier: Operating System :: OS Independent
Requires-Python: >=3.7
License-File: LICENSE
